hakuin/__init__.py
hakuin/exceptions.py
hakuin/extractor.py
hakuin/model.py
hakuin/requesters.py
hakuin/search_algorithms.py
hakuin/tree.py
hakuin/utils.py
hakuin/collectors/__init__.py
hakuin/collectors/checks.py
hakuin/collectors/column_collectors.py
hakuin/collectors/contexts.py
hakuin/collectors/stats.py
hakuin/collectors/builders/__init__.py
hakuin/collectors/builders/collector_builder.py
hakuin/collectors/builders/float_collector_builder.py
hakuin/collectors/builders/int_collector_builder.py
hakuin/collectors/builders/string_collector_builders.py
hakuin/collectors/char_collectors/__init__.py
hakuin/collectors/char_collectors/binary_char_collectors.py
hakuin/collectors/char_collectors/char_collector.py
hakuin/collectors/char_collectors/list_char_collectors.py
hakuin/collectors/char_collectors/model_char_collectors.py
hakuin/collectors/row_collectors/__init__.py
hakuin/collectors/row_collectors/auto_inc_row_collector.py
hakuin/collectors/row_collectors/binary_row_collector.py
hakuin/collectors/row_collectors/float_row_collector.py
hakuin/collectors/row_collectors/guessing_row_collector.py
hakuin/collectors/row_collectors/int_row_collector.py
hakuin/collectors/row_collectors/row_collector.py
hakuin/collectors/row_collectors/string_row_collectors.py
hakuin/dbms/__init__.py
hakuin/dbms/dbms.py
hakuin/dbms/mssql.py
hakuin/dbms/mysql.py
hakuin/dbms/oracle.py
hakuin/dbms/postgres.py
hakuin/dbms/sqlite.py
hakuin/hk.py
hakuin/models/model_columns.pkl
hakuin/models/model_schemas.pkl
hakuin/models/model_tables.pkl
hakuin/models/train_models.py
hakuin-0.2.2.dist-info/METADATA
hakuin-0.2.2.dist-info/WHEEL
hakuin-0.2.2.dist-info/entry_points.txt
hakuin-0.2.2.dist-info/licenses/LICENSE
hakuin-0.2.2.dist-info/RECORD
