Metadata-Version: 2.4
Name: hakuin
Version: 0.2.2
Summary: Blind SQL Injection optimization and automation framework
Project-URL: Homepage, https://github.com/pruzko/hakuin
Author-email: Jakub Pruzinec <j.pruzinec@gmail.com>
License-File: LICENSE
Classifier: License :: OSI Approved :: MIT License
Classifier: Operating System :: OS Independent
Classifier: Programming Language :: Python :: 3
Requires-Python: >=3.6
Requires-Dist: aiohttp
Requires-Dist: nltk
Requires-Dist: sqlglot>=26.4.1
Requires-Dist: tqdm
